CHANGES.markdown
LICENSE
MANIFEST.in
README.md
setup.py
openaps_contrib.egg-info/PKG-INFO
openaps_contrib.egg-info/SOURCES.txt
openaps_contrib.egg-info/dependency_links.txt
openaps_contrib.egg-info/namespace_packages.txt
openaps_contrib.egg-info/not-zip-safe
openaps_contrib.egg-info/requires.txt
openaps_contrib.egg-info/top_level.txt
openapscontrib/__init__.py
openapscontrib/plugins/__init__.py
openapscontrib/timezones/__init__.py