Metadata-Version: 1.1
Name: openaps-contrib
Version: 0.0.12
Summary: openaps contrib namespace package
Home-page: http://github.com/openaps/openaps-contrib
Author: Ben West
Author-email: bewest+openaps@gmail.com
License: MIT
Download-URL: http://pypi.python.org/pypi/openaps-contrib
Platform: any
Classifier: Development Status :: 4 - Beta
Classifier: Environment :: Console
Classifier: Environment :: Web Environment
Classifier: Intended Audience :: Developers
Classifier: License :: OSI Approved :: MIT License
Classifier: Operating System :: OS Independent
Classifier: Programming Language :: Python
Classifier: Topic :: Documentation
Classifier: Topic :: Utilities
